odoo8_addon_business_requirement_deliverable_categ-8.0.3.0.2.99.dev14-py2.7-nspkg.pth
odoo8_addon_business_requirement_deliverable_categ-8.0.3.0.2.99.dev14.dist-info/METADATA
odoo8_addon_business_requirement_deliverable_categ-8.0.3.0.2.99.dev14.dist-info/RECORD
odoo8_addon_business_requirement_deliverable_categ-8.0.3.0.2.99.dev14.dist-info/WHEEL
odoo8_addon_business_requirement_deliverable_categ-8.0.3.0.2.99.dev14.dist-info/namespace_packages.txt
odoo8_addon_business_requirement_deliverable_categ-8.0.3.0.2.99.dev14.dist-info/top_level.txt
odoo_addons/business_requirement_deliverable_categ/README.rst
odoo_addons/business_requirement_deliverable_categ/__init__.py
odoo_addons/business_requirement_deliverable_categ/__openerp__.py
odoo_addons/business_requirement_deliverable_categ/i18n/business_requirement_deliverable_categ.pot
odoo_addons/business_requirement_deliverable_categ/i18n/sl.po
odoo_addons/business_requirement_deliverable_categ/models/__init__.py
odoo_addons/business_requirement_deliverable_categ/models/business_requirement_deliverable_categ.py
odoo_addons/business_requirement_deliverable_categ/static/description/icon.png
odoo_addons/business_requirement_deliverable_categ/static/img/bus_req_category.png
odoo_addons/business_requirement_deliverable_categ/views/business_requirement_deliverable_categ.xml
