Metadata-Version: 2.1
Name: odoo8-addon-business-requirement-deliverable-categ
Version: 8.0.3.0.2.99.dev14
Summary: Adds Task Categories to your Business Requirement Resources
Home-page: https://www.elico-corp.com/
Author: Elico Corp, Odoo Community Association (OCA)
Author-email: support@odoo-community.org
License: AGPL-3
Platform: UNKNOWN
Classifier: Programming Language :: Python
Classifier: Framework :: Odoo
Classifier: License :: OSI Approved :: GNU Affero General Public License v3
Requires-Python: ~=2.7
Requires-Dist: odoo8-addon-business-requirement-deliverable
Requires-Dist: odoo8-addon-project-categ
Requires-Dist: odoo (<9.0a,>=8.0a)
